utia_mint/__init__.py
utia_mint/mint/__init__.py
utia_mint/mint/mint.py
utia_mint/mintdoi.py
utia_mint-0.1.0.dist-info/METADATA
utia_mint-0.1.0.dist-info/WHEEL
utia_mint-0.1.0.dist-info/entry_points.txt
utia_mint-0.1.0.dist-info/RECORD
